ppw_util/config/__init__.py
ppw_util/dict/__init__.py
ppw_util/es/__init__.py
ppw_util/file/__init__.py
ppw_util/lark/__init__.py
ppw_util/log/__init__.py
ppw_util/mongo/__init__.py
ppw_util/mysql/__init__.py
ppw_util/rabbitmq/__init__.py
ppw_util-1.0.1.dist-info/METADATA
ppw_util-1.0.1.dist-info/WHEEL
ppw_util-1.0.1.dist-info/top_level.txt
ppw_util-1.0.1.dist-info/RECORD
